main.py
openapi_slice_mcp-0.2.1.dist-info/licenses/LICENSE
openapi_slice_mcp-0.2.1.dist-info/METADATA
openapi_slice_mcp-0.2.1.dist-info/WHEEL
openapi_slice_mcp-0.2.1.dist-info/entry_points.txt
openapi_slice_mcp-0.2.1.dist-info/top_level.txt
openapi_slice_mcp-0.2.1.dist-info/RECORD
