Metadata-Version: 2.4
Name: openapi-slice-mcp
Version: 0.2.1
Summary: MCP server that extracts relevant portions of OpenAPI specs for specific endpoints, reducing context size when working with large API specifications
Author-email: OpenAPI Slice MCP <maciek@ultraview.pl>
License: MIT
Project-URL: Homepage, https://github.com/vvarp/openapi-slice-mcp
Project-URL: Repository, https://github.com/vvarp/openapi-slice-mcp
Keywords: mcp,openapi,api
Classifier: Development Status :: 4 - Beta
Classifier: Intended Audience :: Developers
Classifier: Topic :: Software Development :: Libraries :: Python Modules
Classifier: Topic :: Internet :: WWW/HTTP :: Dynamic Content
Classifier: Programming Language :: Python :: 3
Classifier: Programming Language :: Python :: 3.12
Requires-Python: >=3.12
License-File: LICENSE
Requires-Dist: fastmcp>=2.10.6
Requires-Dist: pyyaml>=6.0
Requires-Dist: httpx>=0.27.0
Requires-Dist: uvicorn>=0.30.0
Dynamic: license-file
